{
  "ruleset": "5e-2024",
  "results": [
    {
      "name": "Aasimar",
      "source": "XPHB",
      "edition": "one",
      "size": [
        "S",
        "M"
      ],
      "speed": 30,
      "entries": [
        {
          "type": "entries",
          "name": "Celestial Resistance",
          "entries": [
            "You have {@variantrule Resistance|XPHB} to Necrotic damage and Radiant damage."
          ]
        },
        {
          "type": "entries",
          "name": "Darkvision",
          "entries": [
            "You have {@sense Darkvision|XPHB} with a range of 60 feet."
          ]
        },
        {
          "type": "entries",
          "name": "Healing Hands",
          "entries": [
            "As a {@action Magic|XPHB} action, you touch a creature and roll a number of d4s equal to your {@variantrule Proficiency|XPHB|Proficiency Bonus}. The creature regains a number of {@variantrule Hit Points|XPHB} equal to the total rolled. Once you use this trait, you can't use it again until you finish a {@variantrule Long Rest|XPHB}."
          ]
        },
        {
          "type": "entries",
          "name": "Light Bearer",
          "entries": [
            "You know the {@spell Light|XPHB} cantrip. Charisma is your spellcasting ability for it."
          ]
        },
        {
          "type": "entries",
          "name": "Celestial Revelation",
          "entries": [
            "When you reach character level 3, you can transform as a {@variantrule Bonus Action|XPHB} using one of the options below (choose the option each time you transform). The transformation lasts for 1 minute or until you end it (no action required). Once you transform, you can't do so again until you finish a {@variantrule Long Rest|XPHB}.",
            "Once on each of your turns before the transformation ends, you can deal extra damage to one target when you deal damage to it with an attack or a spell. The extra damage equals your {@variantrule Proficiency|XPHB|Proficiency Bonus}, and the extra damage's type is either Necrotic for Necrotic Shroud or Radiant for Heavenly Wings and Inner Radiance.",
            "Here are the transformation options:",
            {
              "type": "list",
              "style": "list-hang-notitle",
              "items": [
                {
                  "type": "item",
                  "name": "Heavenly Wings",
                  "entries": [
                    "Two spectral wings sprout from your back temporarily. Until the transformation ends, you have a {@variantrule Fly Speed|XPHB} equal to your {@variantrule Speed|XPHB}."
                  ]
                },
                {
                  "type": "item",
                  "name": "Inner Radiance",
                  "entries": [
                    "Searing light temporarily radiates from your eyes and mouth. For the duration, you shed {@variantrule Bright Light|XPHB} in a 10-foot radius and {@variantrule Dim Light|XPHB} for an additional 10 feet, and at the end of each of your turns, each creature within 10 feet of you takes Radiant damage equal to your {@variantrule Proficiency|XPHB|Proficiency Bonus}."
                  ]
                },
                {
                  "type": "item",
                  "name": "Necrotic Shroud",
                  "entries": [
                    "Your eyes briefly become pools of darkness, and flightless wings sprout from your back temporarily. Creatures other than your allies within 10 feet of you must succeed on a Charisma saving throw ({@dc 8} plus your Charisma modifier and {@variantrule Proficiency|XPHB|Proficiency Bonus}) or have the {@condition Frightened|XPHB} condition until the end of your next turn."
                  ]
                }
              ]
            }
          ]
        }
      ]
    },
    {
      "name": "Changeling",
      "source": "EFA",
      "edition": "one",
      "size": [
        "S",
        "M"
      ],
      "speed": 30,
      "skillProficiencies": [
        {
          "choose": {
            "from": [
              "deception",
              "insight",
              "intimidation",
              "persuasion"
            ],
            "count": 2
          }
        }
      ],
      "entries": [
        {
          "type": "entries",
          "name": "Changeling Instincts",
          "entries": [
            "Thanks to your connection to the fey realm, you gain proficiency in two of the following skills of your choice: {@skill Deception|XPHB}, {@skill Insight|XPHB}, {@skill Intimidation|XPHB}, {@skill Performance|XPHB}, or {@skill Persuasion|XPHB}."
          ]
        },
        {
          "type": "entries",
          "name": "Shape-Shifter",
          "entries": [
            "As an action, you can shape-shift to change your appearance and your voice. You determine the specifics of the changes, including your coloration, hair length, and sex. You can also adjust your height and weight and can change your size between Medium and Small. You can make yourself appear as a member of another playable species, though none of your game statistics change. You can't duplicate the appearance of an individual you've never seen, and you must adopt a form that has the same basic arrangement of limbs that you have. This trait doesn't change your clothing and equipment.",
            "While shape-shifted with this trait, you have {@variantrule Advantage|XPHB} on Charisma checks.",
            "You stay in the new form until you take an action to revert to your true form."
          ]
        }
      ]
    },
    {
      "name": "Dragonborn",
      "source": "XPHB",
      "edition": "one",
      "size": [
        "M"
      ],
      "speed": 30,
      "entries": [
        {
          "type": "entries",
          "name": "Draconic Ancestry",
          "entries": [
            "Your lineage stems from a dragon progenitor. Choose the kind of dragon from the Draconic Ancestors table. Your choice affects your Breath Weapon and {@variantrule Damage|XPHB} {@variantrule Resistance|XPHB} traits as well as your appearance.",
            {
              "type": "table",
              "caption": "Draconic Ancestors",
              "colLabels": [
                "Dragon",
                "Damage Type"
              ],
              "colStyles": [
                "col-6",
                "col-6"
              ],
              "rows": [
                [
                  "Black",
                  "Acid"
                ],
                [
                  "Blue",
                  "Lightning"
                ],
                [
                  "Brass",
                  "Fire"
                ],
                [
                  "Bronze",
                  "Lightning"
                ],
                [
                  "Copper",
                  "Acid"
                ],
                [
                  "Gold",
                  "Fire"
                ],
                [
                  "Green",
                  "Poison"
                ],
                [
                  "Red",
                  "Fire"
                ],
                [
                  "Silver",
                  "Cold"
                ],
                [
                  "White",
                  "Cold"
                ]
              ]
            }
          ]
        },
        {
          "type": "entries",
          "name": "Breath Weapon",
          "entries": [
            "When you take the {@action Attack|XPHB} action on your turn, you can replace one of your attacks with an exhalation of magical energy in either a 15-foot {@variantrule Cone [Area of Effect]|XPHB|Cone} or a 30-foot {@variantrule Line [Area of Effect]|XPHB|Line} that is 5 feet wide (choose the shape each time). Each creature in that area must make a Dexterity saving throw ({@dc 8} plus your Constitution modifier and {@variantrule Proficiency|XPHB|Proficiency Bonus}). On a failed save, a creature takes {@damage 1d10} damage of the type determined by your Draconic Ancestry trait. On a successful save, a creature takes half as much damage. This damage increases by {@damage 1d10} when you reach character levels 5 ({@damage 2d10}), 11 ({@damage 3d10}), and 17 ({@damage 4d10}).",
            "You can use this Breath Weapon a number of times equal to your {@variantrule Proficiency|XPHB|Proficiency Bonus}, and you regain all expended uses when you finish a {@variantrule Long Rest|XPHB}."
          ]
        },
        {
          "type": "entries",
          "name": "Damage Resistance",
          "entries": [
            "You have {@variantrule Resistance|XPHB} to the damage type determined by your Draconic Ancestry trait."
          ]
        },
        {
          "type": "entries",
          "name": "Darkvision",
          "entries": [
            "You have {@sense Darkvision|XPHB} with a range of 60 feet."
          ]
        },
        {
          "type": "entries",
          "name": "Draconic Flight",
          "entries": [
            "When you reach character level 5, you can channel draconic magic to give yourself temporary flight. As a {@variantrule Bonus Action|XPHB}, you sprout spectral wings on your back that last for 10 minutes or until you retract the wings (no action required) or have the {@condition Incapacitated|XPHB} condition. During that time, you have a {@variantrule Fly Speed|XPHB} equal to your {@variantrule Speed|XPHB}. Your wings appear to be made of the same energy as your Breath Weapon. Once you use this trait, you can't use it again until you finish a {@variantrule Long Rest|XPHB}."
          ]
        }
      ],
      "srd52": true
    },
    {
      "name": "Dwarf",
      "source": "XPHB",
      "edition": "one",
      "size": [
        "M"
      ],
      "speed": 30,
      "entries": [
        {
          "type": "entries",
          "name": "Darkvision",
          "entries": [
            "You have {@sense Darkvision|XPHB} with a range of 120 feet."
          ]
        },
        {
          "type": "entries",
          "name": "Dwarven Resilience",
          "entries": [
            "You have {@variantrule Resistance|XPHB} to Poison damage. You also have {@variantrule Advantage|XPHB} on saving throws you make to avoid or end the {@condition Poisoned|XPHB} condition."
          ]
        },
        {
          "type": "entries",
          "name": "Dwarven Toughness",
          "entries": [
            "Your {@variantrule Hit Points|XPHB|Hit Point} maximum increases by 1, and it increases by 1 again whenever you gain a level."
          ]
        },
        {
          "type": "entries",
          "name": "Stonecunning",
          "entries": [
            "As a {@variantrule Bonus Action|XPHB}, you gain {@sense Tremorsense|XPHB} with a range of 60 feet for 10 minutes. You must be on a stone surface or touching a stone surface to use this {@sense Tremorsense|XPHB}. The stone can be natural or worked.",
            "You can use this {@variantrule Bonus Action|XPHB} a number of times equal to your {@variantrule Proficiency|XPHB|Proficiency Bonus}, and you regain all expended uses when you finish a {@variantrule Long Rest|XPHB}."
          ]
        }
      ],
      "srd52": true
    },
    {
      "name": "Elf",
      "source": "XPHB",
      "edition": "one",
      "size": [
        "M"
      ],
      "speed": 30,
      "skillProficiencies": [
        {
          "choose": {
            "from": [
              "insight",
              "perception",
              "survival"
            ]
          }
        }
      ],
      "entries": [
        {
          "type": "entries",
          "name": "Darkvision",
          "entries": [
            "You have {@sense Darkvision|XPHB} with a range of 60 feet."
          ]
        },
        {
          "type": "entries",
          "name": "Elven Lineage",
          "entries": [
            "You are part of a lineage that grants you supernatural abilities. Choose a lineage from the Elven Lineages table. You gain the level 1 benefit of that lineage.",
            "When you reach character levels 3 and 5, you learn a higher-level spell, as shown on the table. You always have that spell prepared. You can cast it once without a spell slot, and you regain the ability to cast it in that way when you finish a {@variantrule Long Rest|XPHB}. You can also cast the spell using any spell slots you have of the appropriate level.",
            "Intelligence, Wisdom, or Charisma is your spellcasting ability for the spells you cast with this trait (choose the ability when you select the lineage).",
            {
              "type": "table",
              "caption": "Elven Lineages",
              "colLabels": [
                "Lineage",
                "Level 1",
                "Level 3",
                "Level 5"
              ],
              "colStyles": [
                "col-2",
                "col-6",
                "col-2",
                "col-2"
              ],
              "rows": [
                [
                  "Drow",
                  "The range of your {@sense Darkvision|XPHB} increases to 120 feet. You also know the {@spell Dancing Lights|XPHB} cantrip.",
                  "{@spell Faerie Fire|XPHB}",
                  "{@spell Darkness|XPHB}"
                ],
                [
                  "High Elf",
                  "You know the {@spell Prestidigitation|XPHB} cantrip. Whenever you finish a {@variantrule Long Rest|XPHB}, you can replace that cantrip with a different {@filter cantrip from the Wizard spell list|spells|level=0|class=Wizard}.",
                  "{@spell Detect Magic|XPHB}",
                  "{@spell Misty Step|XPHB}"
                ],
                [
                  "Wood Elf",
                  "Your {@variantrule Speed|XPHB} increases to 35 feet. You also know the {@spell Druidcraft|XPHB} cantrip.",
                  "{@spell Longstrider|XPHB}",
                  "{@spell Pass without Trace|XPHB}"
                ]
              ]
            }
          ]
        },
        {
          "type": "entries",
          "name": "Fey Ancestry",
          "entries": [
            "You have {@variantrule Advantage|XPHB} on saving throws you make to avoid or end the {@condition Charmed|XPHB} condition."
          ]
        },
        {
          "type": "entries",
          "name": "Keen Senses",
          "entries": [
            "You have proficiency in the {@skill Insight|XPHB}, {@skill Perception|XPHB}, or {@skill Survival|XPHB} skill."
          ]
        },
        {
          "type": "entries",
          "name": "Trance",
          "entries": [
            "You don't need to sleep, and magic can't put you to sleep. You can finish a {@variantrule Long Rest|XPHB} in 4 hours if you spend those hours in a trancelike meditation, during which you retain consciousness."
          ]
        }
      ],
      "srd52": true
    },
    {
      "name": "Gnome",
      "source": "XPHB",
      "edition": "one",
      "size": [
        "S"
      ],
      "speed": 30,
      "entries": [
        {
          "type": "entries",
          "name": "Darkvision",
          "entries": [
            "You have {@sense Darkvision|XPHB} with a range of 60 feet."
          ]
        },
        {
          "type": "entries",
          "name": "Gnomish Cunning",
          "entries": [
            "You have {@variantrule Advantage|XPHB} on Intelligence, Wisdom, and Charisma saving throws."
          ]
        },
        {
          "type": "entries",
          "name": "Gnomish Lineage",
          "entries": [
            "You are part of a lineage that grants you supernatural abilities. Choose one of the following options; whichever one you choose, Intelligence, Wisdom, or Charisma is your spellcasting ability for the spells you cast with this trait (choose the ability when you select the lineage):",
            {
              "type": "list",
              "style": "list-hang-notitle",
              "items": [
                {
                  "type": "item",
                  "name": "Forest Gnome",
                  "entries": [
                    "You know the {@spell Minor Illusion|XPHB} cantrip. You also always have the {@spell Speak with Animals|XPHB} spell prepared. You can cast it without a spell slot a number of times equal to your {@variantrule Proficiency|XPHB|Proficiency Bonus}, and you regain all expended uses when you finish a {@variantrule Long Rest|XPHB}. You can also use any spell slots you have to cast the spell."
                  ]
                },
                {
                  "type": "item",
                  "name": "Rock Gnome",
                  "entries": [
                    "You know the {@spell Mending|XPHB} and {@spell Prestidigitation|XPHB} cantrips. In addition, you can spend 10 minutes casting {@spell Prestidigitation|XPHB} to create a Tiny clockwork device (AC 5, 1 HP), such as a toy, fire starter, or music box. When you create the device, you determine its function by choosing one effect from {@spell Prestidigitation|XPHB}; the device produces that effect whenever you or another creature takes a {@variantrule Bonus Action|XPHB} to activate it with a touch. If the chosen effect has options within it, you choose one of those options for the device when you create it. For example, if you choose the spell's ignite-extinguish effect, you determine whether the device ignites or extinguishes fire; the device doesn't do both. You can have three such devices in existence at a time, and each falls apart 8 hours after its creation or when you dismantle it with a touch as a {@action Utilize|XPHB} action."
                  ]
                }
              ]
            }
          ]
        }
      ],
      "srd52": true
    },
    {
      "name": "Goliath",
      "source": "XPHB",
      "edition": "one",
      "size": [
        "M"
      ],
      "speed": 35,
      "entries": [
        {
          "type": "entries",
          "name": "Giant Ancestry",
          "entries": [
            "You are descended from Giants. Choose one of the following benefits—a supernatural boon from your ancestry; you can use the chosen benefit a number of times equal to your {@variantrule Proficiency|XPHB|Proficiency Bonus}, and you regain all expended uses when you finish a {@variantrule Long Rest|XPHB}:",
            {
              "type": "list",
              "style": "list-hang-notitle",
              "items": [
                {
                  "type": "item",
                  "name": "Cloud's Jaunt (Cloud Giant)",
                  "entries": [
                    "As a {@variantrule Bonus Action|XPHB}, you magically teleport up to 30 feet to an unoccupied space you can see."
                  ]
                },
                {
                  "type": "item",
                  "name": "Fire's Burn (Fire Giant)",
                  "entries": [
                    "When you hit a target with an attack roll and deal damage to it, you can also deal {@damage 1d10} Fire damage to that target."
                  ]
                },
                {
                  "type": "item",
                  "name": "Frost's Chill (Frost Giant)",
                  "entries": [
                    "When you hit a target with an attack roll and deal damage to it, you can also deal {@damage 1d6} Cold damage to that target and reduce its {@variantrule Speed|XPHB} by 10 feet until the start of your next turn."
                  ]
                },
                {
                  "type": "item",
                  "name": "Hill's Tumble (Hill Giant)",
                  "entries": [
                    "When you hit a Large or smaller creature with an attack roll and deal damage to it, you can give that target the {@condition Prone|XPHB} condition."
                  ]
                },
                {
                  "type": "item",
                  "name": "Stone's Endurance (Stone Giant)",
                  "entries": [
                    "When you take damage, you can take a {@variantrule Reaction|XPHB} to roll {@dice 1d12}. Add your Constitution modifier to the number rolled and reduce the damage by that total."
                  ]
                },
                {
                  "type": "item",
                  "name": "Storm's Thunder (Storm Giant)",
                  "entries": [
                    "When you take damage from a creature within 60 feet of you, you can take a {@variantrule Reaction|XPHB} to deal {@damage 1d8} Thunder damage to that creature."
                  ]
                }
              ]
            }
          ]
        },
        {
          "type": "entries",
          "name": "Large Form",
          "entries": [
            "Starting at character level 5, you can change your size to Large as a {@variantrule Bonus Action|XPHB} if you're in a big enough space. This transformation lasts for 10 minutes or until you end it (no action required). For that duration, you have {@variantrule Advantage|XPHB} on Strength checks, and your {@variantrule Speed|XPHB} increases by 10 feet. Once you use this trait, you can't use it again until you finish a {@variantrule Long Rest|XPHB}."
          ]
        },
        {
          "type": "entries",
          "name": "Powerful Build",
          "entries": [
            "You have {@variantrule Advantage|XPHB} on any ability check you make to end the {@condition Grappled|XPHB} condition. You also count as one size larger when determining your carrying capacity."
          ]
        }
      ],
      "srd52": true
    },
    {
      "name": "Halfling",
      "source": "XPHB",
      "edition": "one",
      "size": [
        "S"
      ],
      "speed": 30,
      "entries": [
        {
          "type": "entries",
          "name": "Brave",
          "entries": [
            "You have {@variantrule Advantage|XPHB} on saving throws you make to avoid or end the {@condition Frightened|XPHB} condition."
          ]
        },
        {
          "type": "entries",
          "name": "Halfling Nimbleness",
          "entries": [
            "You can move through the space of any creature that is a size larger than you, but you can't stop in the same space."
          ]
        },
        {
          "type": "entries",
          "name": "Luck",
          "entries": [
            "When you roll a 1 on the {@dice d20} of a {@variantrule D20 Test|XPHB}, you can reroll the die, and you must use the new roll."
          ]
        },
        {
          "type": "entries",
          "name": "Naturally Stealthy",
          "entries": [
            "You can take the {@action Hide|XPHB} action even when you are obscured only by a creature that is at least one size larger than you."
          ]
        }
      ],
      "srd52": true
    },
    {
      "name": "Human",
      "source": "XPHB",
      "edition": "one",
      "size": [
        "S",
        "M"
      ],
      "speed": 30,
      "skillProficiencies": [
        {
          "any": 1
        }
      ],
      "entries": [
        {
          "type": "entries",
          "name": "Resourceful",
          "entries": [
            "You gain {@variantrule Heroic Inspiration|XPHB} whenever you finish a {@variantrule Long Rest|XPHB}."
          ]
        },
        {
          "type": "entries",
          "name": "Skillful",
          "entries": [
            "You gain proficiency in one skill of your choice."
          ]
        },
        {
          "type": "entries",
          "name": "Versatile",
          "entries": [
            "You gain an {@filter Origin feat|feats|category=o} of your choice."
          ]
        }
      ],
      "srd52": true
    },
    {
      "name": "Kalashtar",
      "source": "EFA",
      "edition": "one",
      "size": [
        "M"
      ],
      "speed": 30,
      "entries": [
        {
          "type": "entries",
          "name": "Dual Mind",
          "entries": [
            "You have {@variantrule Advantage|XPHB} on Wisdom and Charisma saving throws."
          ]
        },
        {
          "type": "entries",
          "name": "Mental Discipline",
          "entries": [
            "You have {@variantrule Resistance|XPHB} to Psychic damage."
          ]
        },
        {
          "type": "entries",
          "name": "Mind Link",
          "entries": [
            "You have telepathy with a range in feet equal to 10 times your level. When you're using this trait to speak telepathically to a creature, you can take a {@action Magic|XPHB} action to give that creature the ability to speak telepathically with you for 1 hour or until you take another {@action Magic|XPHB} action to end this effect."
          ]
        },
        {
          "type": "entries",
          "name": "Severed from Dreams",
          "entries": [
            "You can't be the target of the {@spell Dream|XPHB} spell. In addition, when you finish a {@variantrule Long Rest|XPHB}, you gain proficiency in one skill of your choice. This proficiency lasts until you finish another {@variantrule Long Rest|XPHB}."
          ]
        }
      ]
    },
    {
      "name": "Khoravar",
      "source": "EFA",
      "edition": "one",
      "size": [
        "S",
        "M"
      ],
      "speed": 30,
      "entries": [
        {
          "type": "entries",
          "name": "Darkvision",
          "entries": [
            "You have {@sense Darkvision|XPHB} with a range of 60 feet."
          ]
        },
        {
          "type": "entries",
          "name": "Fey Ancestry",
          "entries": [
            "You have {@variantrule Advantage|XPHB} on saving throws you make to avoid or end the {@condition Charmed|XPHB} condition."
          ]
        },
        {
          "type": "entries",
          "name": "Fey Gift",
          "entries": [
            "You know the {@spell Friends|XPHB} cantrip. Whenever you finish a {@variantrule Long Rest|XPHB}, you can replace that cantrip with a different cantrip from the Cleric, Druid, or Wizard spell list. Intelligence, Wisdom, or Charisma is your spellcasting ability for it (choose the ability when you select this species)."
          ]
        },
        {
          "type": "entries",
          "name": "Lethargy Resilience",
          "entries": [
            "When you fail a saving throw to avoid or end the {@condition Unconscious|XPHB} condition, you can succeed instead. Once you use this trait, you can't do so again until you finish {@dice 1d4} {@variantrule Long Rest|XPHB|Long Rests}."
          ]
        },
        {
          "type": "entries",
          "name": "Skill Versatility",
          "entries": [
            "You gain proficiency in one skill or with one tool of your choice. Whenever you finish a {@variantrule Long Rest|XPHB}, you can replace it with another skill or tool proficiency."
          ]
        }
      ]
    },
    {
      "name": "Orc",
      "source": "XPHB",
      "edition": "one",
      "size": [
        "M"
      ],
      "speed": 30,
      "entries": [
        {
          "type": "entries",
          "name": "Adrenaline Rush",
          "entries": [
            "You can take the {@action Dash|XPHB} action as a {@variantrule Bonus Action|XPHB}. When you do so, you gain a number of {@variantrule Temporary Hit Points|XPHB} equal to your {@variantrule Proficiency|XPHB|Proficiency Bonus}.",
            "You can use this trait a number of times equal to your {@variantrule Proficiency|XPHB|Proficiency Bonus}, and you regain all expended uses when you finish a {@variantrule Short Rest|XPHB|Short} or {@variantrule Long Rest|XPHB}."
          ]
        },
        {
          "type": "entries",
          "name": "Darkvision",
          "entries": [
            "You have {@sense Darkvision|XPHB} with a range of 120 feet."
          ]
        },
        {
          "type": "entries",
          "name": "Relentless Endurance",
          "entries": [
            "When you are reduced to 0 {@variantrule Hit Points|XPHB} but not killed outright, you can drop to 1 {@variantrule Hit Points|XPHB|Hit Point} instead. Once you use this trait, you can't do so again until you finish a {@variantrule Long Rest|XPHB}."
          ]
        }
      ],
      "srd52": true
    },
    {
      "name": "Shifter",
      "source": "EFA",
      "edition": "one",
      "size": [
        "S",
        "M"
      ],
      "speed": 30,
      "skillProficiencies": [
        {
          "choose": {
            "from": [
              "acrobatics",
              "athletics",
              "intimidation",
              "survival"
            ]
          }
        }
      ],
      "entries": [
        {
          "type": "entries",
          "name": "Bestial Instincts",
          "entries": [
            "Channeling the beast within, you gain proficiency in one of the following skills of your choice: {@skill Acrobatics|XPHB}, {@skill Athletics|XPHB}, {@skill Intimidation|XPHB}, or {@skill Survival|XPHB}."
          ]
        },
        {
          "type": "entries",
          "name": "Darkvision",
          "entries": [
            "You have {@sense Darkvision|XPHB} with a range of 60 feet."
          ]
        },
        {
          "type": "entries",
          "name": "Shifting",
          "entries": [
            "As a {@variantrule Bonus Action|XPHB}, you can shape-shift to assume a more bestial appearance. This transformation lasts for 1 minute or until you revert to your normal appearance as a {@variantrule Bonus Action|XPHB}. When you shift, you gain {@variantrule Temporary Hit Points|XPHB} equal to 2 times your {@variantrule Proficiency|XPHB|Proficiency Bonus}. You can shift a number of times equal to your {@variantrule Proficiency|XPHB|Proficiency Bonus}, and you regain all expended uses when you finish a {@variantrule Long Rest|XPHB}.",
            "Whenever you shift, you gain the benefit of one of the following options (choose when you select this species)",
            {
              "type": "list",
              "style": "list-hang-notitle",
              "items": [
                {
                  "type": "item",
                  "name": "Beasthide",
                  "entries": [
                    "You gain {@dice 1d6} additional {@variantrule Temporary Hit Points|XPHB}. While shifted, you have a +1 bonus to your {@variantrule Armor Class|XPHB}."
                  ]
                },
                {
                  "type": "item",
                  "name": "Longtooth",
                  "entries": [
                    "When you shift and as a {@variantrule Bonus Action|XPHB} on your other turns while shifted, you can use your elongated fangs to make an {@variantrule Unarmed Strike|XPHB}. If you hit with this {@variantrule Unarmed Strike|XPHB} and deal damage, you can deal Piercing damage equal to {@dice 1d6} plus your Strength modifier, instead of the normal damage of an {@variantrule Unarmed Strike|XPHB}."
                  ]
                },
                {
                  "type": "item",
                  "name": "Swiftstride",
                  "entries": [
                    "While you are shifted, your {@variantrule Speed|XPHB} increases by 10 feet. Additionally, you can move up to 10 feet as a {@variantrule Reaction|XPHB} when a creature ends its turn within 5 feet of you. This reactive movement doesn't provoke {@action Opportunity Attack|XPHB|Opportunity Attacks}."
                  ]
                },
                {
                  "type": "item",
                  "name": "Wildhunt",
                  "entries": [
                    "While shifted, you have {@variantrule Advantage|XPHB} on Wisdom checks. Additionally, no creature within 30 feet of you can have {@variantrule Advantage|XPHB} on an attack roll against you unless you have the {@condition Incapacitated|XPHB} condition."
                  ]
                }
              ]
            }
          ]
        }
      ]
    },
    {
      "name": "Tiefling",
      "source": "XPHB",
      "edition": "one",
      "size": [
        "S",
        "M"
      ],
      "speed": 30,
      "entries": [
        {
          "type": "entries",
          "name": "Darkvision",
          "entries": [
            "You have {@sense Darkvision|XPHB} with a range of 60 feet."
          ]
        },
        {
          "type": "entries",
          "name": "Fiendish Legacy",
          "entries": [
            "You are the recipient of a legacy that grants you supernatural abilities. Choose a legacy from the Fiendish Legacies table. You gain the level 1 benefit of the chosen legacy.",
            "When you reach character levels 3 and 5, you learn a higher-level spell, as shown on the table. You always have that spell prepared. You can cast it once without a spell slot, and you regain the ability to cast it in that way when you finish a {@variantrule Long Rest|XPHB}. You can also cast the spell using any spell slots you have of the appropriate level. Intelligence, Wisdom, or Charisma is your spellcasting ability for the spells you cast with this trait (choose the ability when you select the legacy).",
            {
              "type": "table",
              "caption": "Fiendish Legacies",
              "colLabels": [
                "Legacy",
                "Level 1",
                "Level 3",
                "Level 5"
              ],
              "colStyles": [
                "col-2",
                "col-6",
                "col-2",
                "col-2"
              ],
              "rows": [
                [
                  "Abyssal",
                  "You have {@variantrule Resistance|XPHB} to Poison damage. You also know the {@spell Poison Spray|XPHB} cantrip.",
                  "{@spell Ray of Sickness|XPHB}",
                  "{@spell Hold Person|XPHB}"
                ],
                [
                  "Chthonic",
                  "You have {@variantrule Resistance|XPHB} to Necrotic damage. You also know the {@spell Chill Touch|XPHB} cantrip.",
                  "{@spell False Life|XPHB}",
                  "{@spell Ray of Enfeeblement|XPHB}"
                ],
                [
                  "Infernal",
                  "You have {@variantrule Resistance|XPHB} to Fire damage. You also know the {@spell Fire Bolt|XPHB} cantrip.",
                  "{@spell Hellish Rebuke|XPHB}",
                  "{@spell Darkness|XPHB}"
                ]
              ]
            }
          ]
        },
        {
          "type": "entries",
          "name": "Otherworldly Presence",
          "entries": [
            "You know the {@spell Thaumaturgy|XPHB} cantrip. When you cast it with this trait, the spell uses the same spellcasting ability you use for your Fiendish Legacy Trait."
          ]
        }
      ],
      "srd52": true
    },
    {
      "name": "Warforged",
      "source": "EFA",
      "edition": "one",
      "size": [
        "S",
        "M"
      ],
      "speed": 30,
      "skillProficiencies": [
        {
          "any": 1
        }
      ],
      "entries": [
        {
          "type": "entries",
          "name": "Construct Resilience",
          "entries": [
            "You have {@variantrule Resistance|XPHB} to Poison damage. You also have {@variantrule Advantage|XPHB} on saving throws to avoid or end the {@condition Poisoned|XPHB} condition."
          ]
        },
        {
          "type": "entries",
          "name": "Integrated Protection",
          "entries": [
            "You gain a +1 bonus to your {@variantrule Armor Class|XPHB}. In addition, armor you have donned can't be removed against your will while you're alive."
          ]
        },
        {
          "type": "entries",
          "name": "Sentry's Rest",
          "entries": [
            "You don't need to sleep, and magic can't put you to sleep. You can finish a {@variantrule Long Rest|XPHB} in 6 hours if you spend those hours in an inactive, motionless state. During this time, you appear inert but remain conscious."
          ]
        },
        {
          "type": "entries",
          "name": "Specialized Design",
          "entries": [
            "You gain one skill proficiency and one tool proficiency of your choice."
          ]
        },
        {
          "type": "entries",
          "name": "Tireless",
          "entries": [
            "You don't gain {@condition Exhaustion|XPHB} levels from dehydration, malnutrition, or suffocation."
          ]
        }
      ]
    }
  ]
}
